LICENSE
README.md
setup.cfg
setup.py
embedded_tools/__init__.py
embedded_tools.egg-info/PKG-INFO
embedded_tools.egg-info/SOURCES.txt
embedded_tools.egg-info/dependency_links.txt
embedded_tools.egg-info/requires.txt
embedded_tools.egg-info/top_level.txt
embedded_tools/implementations/__init__.py
embedded_tools/implementations/console_posix.py
embedded_tools/implementations/console_x64.py
embedded_tools/implementations/jlink.py
embedded_tools/implementations/openocd.py
embedded_tools/implementations/rtt.py
embedded_tools/implementations/serial_port.py
embedded_tools/interfaces/__init__.py
embedded_tools/interfaces/console.py
embedded_tools/interfaces/debugger.py
embedded_tools/interfaces/serial.py